pyschemavalidator/__init__.py
pyschemavalidator/parameters.py
pyschemavalidator/validators.py
pyschemavalidator-1.0.4.dist-info/LICENSE
pyschemavalidator-1.0.4.dist-info/METADATA
pyschemavalidator-1.0.4.dist-info/WHEEL
pyschemavalidator-1.0.4.dist-info/top_level.txt
pyschemavalidator-1.0.4.dist-info/RECORD
