Metadata-Version: 2.1
Name: pyschemavalidator
Version: 1.0.4
Summary: Decorator for endpoint inputs on APIs and a dictionary/JSON validator.
Home-page: https://github.com/albarsil/pyschemavalidator
Author: Allan Barcelos
Author-email: albarsil@gmail.com
License: MIT
Keywords: api,flask,graphql,json,validation,schema,dictionary,graphql
Platform: UNKNOWN
Classifier: License :: OSI Approved :: MIT License
Classifier: Programming Language :: Python :: 3.5
Classifier: Programming Language :: Python :: 3.6
Classifier: Programming Language :: Python :: 3.7
Classifier: Programming Language :: Python :: 3.8
Classifier: Programming Language :: Python :: 3.9
License-File: LICENSE
